{
  "name": "gd32",
  "title": "GD GD32",
  "description": "GigaDevice GD32 MCU has many years of industry-leading design experience, as it has already launched a huge variety of 32bit general purpose microcontrollers, based on Arm Cortex-M and RISC-V cores. GigaDevice continues to empower various industry fields, providing high performance and rich in resources MCUs.",
  "homepage": "http://www.gd32mcu.com/en/product",
  "license": "Apache-2.0",
  "keywords": [
    "dev-platform",
    "ARM",
    "Cortex-M",
    "GigaDevice",
    "GD32"
  ],
  "engines": {
    "platformio": "^5"
  },
  "repository": {
    "type": "git",
    "url": "https://github.com/maxgerhardt/platform-gd32"
  },
  "version": "1.0.0",
  "frameworks": {
    "spl": {
      "package": "framework-spl-gd32",
      "script": "builder/frameworks/spl.py",
      "description": "The GigaDevice Standard Peripheral Library provides a set of functions for handling the peripherals on the GD32 family of microcontrollers.",
      "homepage": "http://www.gd32mcu.com/en/download/",
      "title": "Standard Peripheral Library"
    },
    "arduino": {
      "package": "framework-arduinogd32",
      "script": "builder/frameworks/arduino.py",
      "description": "Arduino Wiring-based Framework allows writing cross-platform software to control devices attached to a wide range of Arduino boards to create all kinds of creative coding, interactive objects, spaces or physical experiences",
      "homepage": "https://github.com/maxgerhardt/gd32-arduino-core/",
      "title": "Arduino"
    }
  },
  "packages": {
    "toolchain-gccarmnoneeabi": {
      "type": "toolchain",
      "owner": "platformio",
      "version": "~1.90201.0",
      "optionalVersions": [
        "~1.60301.0",
        "~1.80201.0",
        "~1.90201.0"
      ]
    },
    "framework-spl-gd32": {
      "type": "framework",
      "optional": true,
      "owner": "maxgerhardt",
      "version": "~2.10000.0"
    },
    "framework-arduinogd32": {
      "type": "framework",
      "optional": true,
      "owner": "maxgerhardt",
      "version": "~4.10000.0"
    },
    "tool-stm32duino": {
      "type": "uploader",
      "optional": true,
      "owner": "platformio",
      "version": "~1.0.1"
    },
    "tool-openocd": {
      "type": "uploader",
      "optional": true,
      "owner": "platformio",
      "version": "~2.1100.0"
    },
    "tool-jlink": {
      "type": "uploader",
      "optional": true,
      "owner": "platformio",
      "version": "^1.63208.0"
    },
    "tool-dfuutil": {
      "type": "uploader",
      "optional": true,
      "owner": "platformio",
      "version": "~1.9.190708"
    }
  }
}
